MANIFEST.in
README.rst
setup.py
collective/__init__.py
collective.wysiwyg_biografy.egg-info/PKG-INFO
collective.wysiwyg_biografy.egg-info/SOURCES.txt
collective.wysiwyg_biografy.egg-info/dependency_links.txt
collective.wysiwyg_biografy.egg-info/entry_points.txt
collective.wysiwyg_biografy.egg-info/namespace_packages.txt
collective.wysiwyg_biografy.egg-info/not-zip-safe
collective.wysiwyg_biografy.egg-info/requires.txt
collective.wysiwyg_biografy.egg-info/top_level.txt
collective/wysiwyg_biografy/__init__.py
collective/wysiwyg_biografy/configure.zcml
collective/wysiwyg_biografy/interfaces.py
collective/wysiwyg_biografy/browser/__init__.py
collective/wysiwyg_biografy/browser/configure.zcml
collective/wysiwyg_biografy/browser/personal_information.py
collective/wysiwyg_biografy/profiles/default/browserlayer.xml
collective/wysiwyg_biografy/profiles/default/metadata.xml
collective/wysiwyg_biografy/profiles/default/skins.xml
collective/wysiwyg_biografy/profiles/uninstall/browserlayer.xml
collective/wysiwyg_biografy/profiles/uninstall/skins.xml
collective/wysiwyg_biografy/skins/wysiwyg_biografy/author.cpt
collective/wysiwyg_biografy/skins/wysiwyg_biografy/author.cpt.metadata
collective/wysiwyg_biografy/skins/wysiwyg_biografy/personalize_form.cpt
collective/wysiwyg_biografy/skins/wysiwyg_biografy/personalize_form.cpt.metadata
docs/HISTORY.rst
docs/INSTALL.txt
docs/LICENSE.GPL
docs/LICENSE.txt