Metadata-Version: 1.0
Name: collective.wysiwyg-biografy
Version: 0.2.0
Summary: The Plone user's biografy using the WYSIWYG editor
Home-page: http://plone.org/products/collective.wysiwyg_biografy
Author: RedTurtle Technology
Author-email: sviluppoplone@redturtle.it
License: GPL
Keywords: plone biografy wysiwyg editor
Platform: UNKNOWN
Classifier: Framework :: Plone
Classifier: Framework :: Plone :: 4.3
Classifier: Programming Language :: Python
Classifier: Development Status :: 4 - Beta
